[
  {
    "version": "7.2.0-beta.0",
    "timestamp": "2025-11-18T01:57:39.333Z",
    "publicationDate": "2025-10-28T05:01:04.958Z",
    "files": [
      {
        "path": "assets/BarChart-s5B9cjAo.js",
        "size": 341230,
        "type": "js"
      },
      {
        "path": "assets/DependentsPage-W_hbI_Xz.js",
        "size": 16679,
        "type": "js"
      },
      {
        "path": "assets/HomePage-Jk1bULgb.js",
        "size": 3646,
        "type": "js"
      },
      {
        "path": "assets/MinificationBenchmarksPage-cdEYAexl.js",
        "size": 10060,
        "type": "js"
      },
      {
        "path": "assets/NpmPackagesPage-v6Mh_c1D.js",
        "size": 7306,
        "type": "js"
      },
      {
        "path": "assets/PageContainer-B4Zsf9vs.js",
        "size": 670,
        "type": "js"
      },
      {
        "path": "assets/RolldownStatsPage-BNPAt_tF.js",
        "size": 50386,
        "type": "js"
      },
      {
        "path": "assets/index-2yHSxcBe.js",
        "size": 232927,
        "type": "js"
      },
      {
        "path": "assets/index-CCl_Pi0d.css",
        "size": 39533,
        "type": "css"
      },
      {
        "path": "assets/trending-up-CUMxkCut.js",
        "size": 280,
        "type": "js"
      },
      {
        "path": "index.html",
        "size": 515,
        "type": "html"
      },
      {
        "path": "vite.svg",
        "size": 1497,
        "type": "other"
      }
    ],
    "totalSize": 704729,
    "buildTime": 941
  },
  {
    "version": "7.2.0-beta.1",
    "timestamp": "2025-11-18T01:57:42.623Z",
    "publicationDate": "2025-11-04T04:03:56.914Z",
    "files": [
      {
        "path": "assets/BarChart-s5B9cjAo.js",
        "size": 341230,
        "type": "js"
      },
      {
        "path": "assets/DependentsPage-W_hbI_Xz.js",
        "size": 16679,
        "type": "js"
      },
      {
        "path": "assets/HomePage-Jk1bULgb.js",
        "size": 3646,
        "type": "js"
      },
      {
        "path": "assets/MinificationBenchmarksPage-cdEYAexl.js",
        "size": 10060,
        "type": "js"
      },
      {
        "path": "assets/NpmPackagesPage-v6Mh_c1D.js",
        "size": 7306,
        "type": "js"
      },
      {
        "path": "assets/PageContainer-B4Zsf9vs.js",
        "size": 670,
        "type": "js"
      },
      {
        "path": "assets/RolldownStatsPage-BNPAt_tF.js",
        "size": 50386,
        "type": "js"
      },
      {
        "path": "assets/index-2yHSxcBe.js",
        "size": 232927,
        "type": "js"
      },
      {
        "path": "assets/index-CCl_Pi0d.css",
        "size": 39533,
        "type": "css"
      },
      {
        "path": "assets/trending-up-CUMxkCut.js",
        "size": 280,
        "type": "js"
      },
      {
        "path": "index.html",
        "size": 515,
        "type": "html"
      },
      {
        "path": "vite.svg",
        "size": 1497,
        "type": "other"
      }
    ],
    "totalSize": 704729,
    "buildTime": 893
  },
  {
    "version": "7.2.0-beta.2",
    "timestamp": "2025-11-18T01:57:45.851Z",
    "publicationDate": "2025-11-04T04:27:18.873Z",
    "files": [
      {
        "path": "assets/BarChart-CFbluXqx.js",
        "size": 341741,
        "type": "js"
      },
      {
        "path": "assets/DependentsPage-CkVxXO0S.js",
        "size": 16679,
        "type": "js"
      },
      {
        "path": "assets/HomePage-DgP01-HE.js",
        "size": 3646,
        "type": "js"
      },
      {
        "path": "assets/MinificationBenchmarksPage-dQjhiaqq.js",
        "size": 10060,
        "type": "js"
      },
      {
        "path": "assets/NpmPackagesPage-CM9ORV9X.js",
        "size": 7306,
        "type": "js"
      },
      {
        "path": "assets/PageContainer-CPjTSLIr.js",
        "size": 670,
        "type": "js"
      },
      {
        "path": "assets/RolldownStatsPage-DCsrxgXd.js",
        "size": 50386,
        "type": "js"
      },
      {
        "path": "assets/index-CCl_Pi0d.css",
        "size": 39533,
        "type": "css"
      },
      {
        "path": "assets/index-T7ljJEwc.js",
        "size": 233395,
        "type": "js"
      },
      {
        "path": "assets/trending-up-DKecAtST.js",
        "size": 280,
        "type": "js"
      },
      {
        "path": "index.html",
        "size": 515,
        "type": "html"
      },
      {
        "path": "vite.svg",
        "size": 1497,
        "type": "other"
      }
    ],
    "totalSize": 705708,
    "buildTime": 836
  },
  {
    "version": "7.2.0-beta.3",
    "timestamp": "2025-11-18T01:57:48.834Z",
    "publicationDate": "2025-11-05T06:12:37.945Z",
    "files": [
      {
        "path": "assets/BarChart-CUWdfuw8.js",
        "size": 341741,
        "type": "js"
      },
      {
        "path": "assets/DependentsPage-YhhmDgXH.js",
        "size": 16679,
        "type": "js"
      },
      {
        "path": "assets/HomePage-D51KSz07.js",
        "size": 3646,
        "type": "js"
      },
      {
        "path": "assets/MinificationBenchmarksPage-ChClBAHT.js",
        "size": 10060,
        "type": "js"
      },
      {
        "path": "assets/NpmPackagesPage-Dgrt9pRn.js",
        "size": 7306,
        "type": "js"
      },
      {
        "path": "assets/PageContainer-BlR5Eegm.js",
        "size": 670,
        "type": "js"
      },
      {
        "path": "assets/RolldownStatsPage-B0i-bvDM.js",
        "size": 50386,
        "type": "js"
      },
      {
        "path": "assets/index-CCl_Pi0d.css",
        "size": 39533,
        "type": "css"
      },
      {
        "path": "assets/index-DpF85XUH.js",
        "size": 233395,
        "type": "js"
      },
      {
        "path": "assets/trending-up-Dp8-vm9F.js",
        "size": 280,
        "type": "js"
      },
      {
        "path": "index.html",
        "size": 515,
        "type": "html"
      },
      {
        "path": "vite.svg",
        "size": 1497,
        "type": "other"
      }
    ],
    "totalSize": 705708,
    "buildTime": 795
  },
  {
    "version": "7.2.0",
    "timestamp": "2025-11-18T01:57:51.825Z",
    "publicationDate": "2025-11-05T08:46:05.916Z",
    "files": [
      {
        "path": "assets/BarChart-CUWdfuw8.js",
        "size": 341741,
        "type": "js"
      },
      {
        "path": "assets/DependentsPage-YhhmDgXH.js",
        "size": 16679,
        "type": "js"
      },
      {
        "path": "assets/HomePage-D51KSz07.js",
        "size": 3646,
        "type": "js"
      },
      {
        "path": "assets/MinificationBenchmarksPage-ChClBAHT.js",
        "size": 10060,
        "type": "js"
      },
      {
        "path": "assets/NpmPackagesPage-Dgrt9pRn.js",
        "size": 7306,
        "type": "js"
      },
      {
        "path": "assets/PageContainer-BlR5Eegm.js",
        "size": 670,
        "type": "js"
      },
      {
        "path": "assets/RolldownStatsPage-B0i-bvDM.js",
        "size": 50386,
        "type": "js"
      },
      {
        "path": "assets/index-CCl_Pi0d.css",
        "size": 39533,
        "type": "css"
      },
      {
        "path": "assets/index-DpF85XUH.js",
        "size": 233395,
        "type": "js"
      },
      {
        "path": "assets/trending-up-Dp8-vm9F.js",
        "size": 280,
        "type": "js"
      },
      {
        "path": "index.html",
        "size": 515,
        "type": "html"
      },
      {
        "path": "vite.svg",
        "size": 1497,
        "type": "other"
      }
    ],
    "totalSize": 705708,
    "buildTime": 798
  },
  {
    "version": "7.2.1",
    "timestamp": "2025-11-18T01:57:54.808Z",
    "publicationDate": "2025-11-06T04:05:09.203Z",
    "files": [
      {
        "path": "assets/BarChart-CUWdfuw8.js",
        "size": 341741,
        "type": "js"
      },
      {
        "path": "assets/DependentsPage-YhhmDgXH.js",
        "size": 16679,
        "type": "js"
      },
      {
        "path": "assets/HomePage-D51KSz07.js",
        "size": 3646,
        "type": "js"
      },
      {
        "path": "assets/MinificationBenchmarksPage-ChClBAHT.js",
        "size": 10060,
        "type": "js"
      },
      {
        "path": "assets/NpmPackagesPage-Dgrt9pRn.js",
        "size": 7306,
        "type": "js"
      },
      {
        "path": "assets/PageContainer-BlR5Eegm.js",
        "size": 670,
        "type": "js"
      },
      {
        "path": "assets/RolldownStatsPage-B0i-bvDM.js",
        "size": 50386,
        "type": "js"
      },
      {
        "path": "assets/index-CCl_Pi0d.css",
        "size": 39533,
        "type": "css"
      },
      {
        "path": "assets/index-DpF85XUH.js",
        "size": 233395,
        "type": "js"
      },
      {
        "path": "assets/trending-up-Dp8-vm9F.js",
        "size": 280,
        "type": "js"
      },
      {
        "path": "index.html",
        "size": 515,
        "type": "html"
      },
      {
        "path": "vite.svg",
        "size": 1497,
        "type": "other"
      }
    ],
    "totalSize": 705708,
    "buildTime": 833
  },
  {
    "version": "7.2.2",
    "timestamp": "2025-11-18T01:57:57.776Z",
    "publicationDate": "2025-11-07T06:55:16.845Z",
    "files": [
      {
        "path": "assets/BarChart-CUWdfuw8.js",
        "size": 341230,
        "type": "js"
      },
      {
        "path": "assets/DependentsPage-YhhmDgXH.js",
        "size": 16679,
        "type": "js"
      },
      {
        "path": "assets/HomePage-D51KSz07.js",
        "size": 3646,
        "type": "js"
      },
      {
        "path": "assets/MinificationBenchmarksPage-ChClBAHT.js",
        "size": 10060,
        "type": "js"
      },
      {
        "path": "assets/NpmPackagesPage-Dgrt9pRn.js",
        "size": 7306,
        "type": "js"
      },
      {
        "path": "assets/PageContainer-BlR5Eegm.js",
        "size": 670,
        "type": "js"
      },
      {
        "path": "assets/RolldownStatsPage-B0i-bvDM.js",
        "size": 50386,
        "type": "js"
      },
      {
        "path": "assets/index-CCl_Pi0d.css",
        "size": 39533,
        "type": "css"
      },
      {
        "path": "assets/index-DpF85XUH.js",
        "size": 232758,
        "type": "js"
      },
      {
        "path": "assets/trending-up-Dp8-vm9F.js",
        "size": 280,
        "type": "js"
      },
      {
        "path": "index.html",
        "size": 515,
        "type": "html"
      },
      {
        "path": "vite.svg",
        "size": 1497,
        "type": "other"
      }
    ],
    "totalSize": 704560,
    "buildTime": 796
  },
  {
    "version": "7.2.3",
    "timestamp": "2025-11-18T01:58:00.721Z",
    "publicationDate": "2025-11-11T02:45:30.039Z",
    "files": [
      {
        "path": "assets/BarChart-BG2_Jlsm.js",
        "size": 341218,
        "type": "js"
      },
      {
        "path": "assets/DependentsPage-DX____WL.js",
        "size": 16667,
        "type": "js"
      },
      {
        "path": "assets/HomePage-HmZinTbT.js",
        "size": 3629,
        "type": "js"
      },
      {
        "path": "assets/MinificationBenchmarksPage-DiaqFIb6.js",
        "size": 10043,
        "type": "js"
      },
      {
        "path": "assets/NpmPackagesPage-CyU2mUA2.js",
        "size": 7289,
        "type": "js"
      },
      {
        "path": "assets/PageContainer-D2p92CIy.js",
        "size": 665,
        "type": "js"
      },
      {
        "path": "assets/RolldownStatsPage-UFUo0nzU.js",
        "size": 50378,
        "type": "js"
      },
      {
        "path": "assets/index-Bhz8yaIg.js",
        "size": 232748,
        "type": "js"
      },
      {
        "path": "assets/index-CCl_Pi0d.css",
        "size": 39533,
        "type": "css"
      },
      {
        "path": "assets/trending-up-DQhEQ4pW.js",
        "size": 280,
        "type": "js"
      },
      {
        "path": "index.html",
        "size": 515,
        "type": "html"
      },
      {
        "path": "vite.svg",
        "size": 1497,
        "type": "other"
      }
    ],
    "totalSize": 704462,
    "buildTime": 824
  },
  {
    "version": "7.2.4",
    "timestamp": "2025-11-18T01:58:03.915Z",
    "publicationDate": "2025-11-11T11:11:00.522Z",
    "files": [
      {
        "path": "assets/BarChart-BG2_Jlsm.js",
        "size": 341218,
        "type": "js"
      },
      {
        "path": "assets/DependentsPage-DX____WL.js",
        "size": 16667,
        "type": "js"
      },
      {
        "path": "assets/HomePage-HmZinTbT.js",
        "size": 3629,
        "type": "js"
      },
      {
        "path": "assets/MinificationBenchmarksPage-DiaqFIb6.js",
        "size": 10043,
        "type": "js"
      },
      {
        "path": "assets/NpmPackagesPage-CyU2mUA2.js",
        "size": 7289,
        "type": "js"
      },
      {
        "path": "assets/PageContainer-D2p92CIy.js",
        "size": 665,
        "type": "js"
      },
      {
        "path": "assets/RolldownStatsPage-UFUo0nzU.js",
        "size": 50378,
        "type": "js"
      },
      {
        "path": "assets/index-Bhz8yaIg.js",
        "size": 232748,
        "type": "js"
      },
      {
        "path": "assets/index-CCl_Pi0d.css",
        "size": 39533,
        "type": "css"
      },
      {
        "path": "assets/trending-up-DQhEQ4pW.js",
        "size": 280,
        "type": "js"
      },
      {
        "path": "index.html",
        "size": 515,
        "type": "html"
      },
      {
        "path": "vite.svg",
        "size": 1497,
        "type": "other"
      }
    ],
    "totalSize": 704462,
    "buildTime": 800
  },
  {
    "version": "7.2.5",
    "timestamp": "2025-11-18T01:58:06.875Z",
    "publicationDate": "2025-11-12T11:18:40.975Z",
    "files": [
      {
        "path": "assets/BarChart-w35nX8Na.js",
        "size": 341218,
        "type": "js"
      },
      {
        "path": "assets/DependentsPage-BHr4wlV-.js",
        "size": 16667,
        "type": "js"
      },
      {
        "path": "assets/HomePage-HUmfuONl.js",
        "size": 3629,
        "type": "js"
      },
      {
        "path": "assets/MinificationBenchmarksPage-BwJVJhhv.js",
        "size": 10043,
        "type": "js"
      },
      {
        "path": "assets/NpmPackagesPage-DiIUgMcw.js",
        "size": 7289,
        "type": "js"
      },
      {
        "path": "assets/PageContainer-C3XtAoTb.js",
        "size": 665,
        "type": "js"
      },
      {
        "path": "assets/RolldownStatsPage-CxDjpIvg.js",
        "size": 50378,
        "type": "js"
      },
      {
        "path": "assets/index-CCl_Pi0d.css",
        "size": 39533,
        "type": "css"
      },
      {
        "path": "assets/index-LqdidUxX.js",
        "size": 232748,
        "type": "js"
      },
      {
        "path": "assets/trending-up-BuDdUPxT.js",
        "size": 280,
        "type": "js"
      },
      {
        "path": "index.html",
        "size": 515,
        "type": "html"
      },
      {
        "path": "vite.svg",
        "size": 1497,
        "type": "other"
      }
    ],
    "totalSize": 704462,
    "buildTime": 783
  }
]